timeseriesencoder/__init__.py
timeseriesencoder/encoders/__init__.py
timeseriesencoder/encoders/numeric_encoder.py
timeseriesencoder/encoders/time_series_encoder.py
timeseriesencoder-0.2.42.dist-info/LICENSE
timeseriesencoder-0.2.42.dist-info/METADATA
timeseriesencoder-0.2.42.dist-info/WHEEL
timeseriesencoder-0.2.42.dist-info/top_level.txt
timeseriesencoder-0.2.42.dist-info/RECORD
