Metadata-Version: 2.1
Name: timeseriesencoder
Version: 0.2.42
Summary: package for encoding and decoding time series in JSON files into embedded base 16, 64, or 91 encodings.
Author: Keith Dyer
Author-email: kilaxen@gmail.com
License: UNKNOWN
Platform: UNKNOWN
Classifier: Programming Language :: Python :: 3
Classifier: License :: OSI Approved :: MIT License
Classifier: Operating System :: OS Independent
Requires-Python: >=3.6
License-File: LICENSE
Requires-Dist: numpy
Requires-Dist: ciso8601
Requires-Dist: numpyencoder
Requires-Dist: pandas
Requires-Dist: sklearn
